elara/__init__.py
elara/main.py
elara/cache/__init__.py
elara/cache/cache.py
elara/context/__init__.py
elara/context/author.py
elara/context/context.py
elara/context/interaction.py
elara/context/reaction.py
elara/embeds/__init__.py
elara/embeds/embeds.py
elara/utils/__init__.py
elara/utils/cog.py
elara/utils/cogmanager.py
elara/utils/commands.py
elara/utils/components.py
elara/utils/events.py
elara/utils/ratelimit.py
elara/ws/__init__.py
elara/ws/auth.py
elara/ws/socket.py
hubber_py-0.1.2.dist-info/METADATA
hubber_py-0.1.2.dist-info/WHEEL
hubber_py-0.1.2.dist-info/top_level.txt
hubber_py-0.1.2.dist-info/RECORD
