Metadata-Version: 2.4
Name: hubber-py
Version: 0.1.2
Summary: A Discord-like bot framework for Hubber
Author-email: lane <rsalol@proton.me>
License: MIT
Project-URL: Homepage, https://github.com/6umb/elara-hubber
Project-URL: Repository, https://github.com/6umb/elara-hubber
Classifier: Programming Language :: Python :: 3
Classifier: License :: OSI Approved :: MIT License
Classifier: Operating System :: OS Independent
Requires-Python: >=3.8
Requires-Dist: aiohttp>=3.8.0
Requires-Dist: websockets>=10.0
